mcp_client.py
mcp_client_multi.py
mseep_ultimate_mcp_client-1.0.1.dist-info/METADATA
mseep_ultimate_mcp_client-1.0.1.dist-info/WHEEL
mseep_ultimate_mcp_client-1.0.1.dist-info/entry_points.txt
mseep_ultimate_mcp_client-1.0.1.dist-info/RECORD
